pyser/__init__.py
pyser/configparser.py
pyser/json.py
pyser-0.1.5.dist-info/LICENSE
pyser-0.1.5.dist-info/METADATA
pyser-0.1.5.dist-info/WHEEL
pyser-0.1.5.dist-info/top_level.txt
pyser-0.1.5.dist-info/RECORD
