Metadata-Version: 2.1
Name: pyser
Version: 0.1.5
Summary: Python Serializer and Deserializer
Home-page: https://github.com/jonnekaunisto/pyser
Author: Jonne Kaunisto
Author-email: jonneka@gmail.com
License: MIT License
Keywords: serialize,deserialize
Platform: UNKNOWN
Classifier: Development Status :: 2 - Pre-Alpha
Classifier: Intended Audience :: Developers
Classifier: License :: OSI Approved :: MIT License
Classifier: Natural Language :: English
Classifier: Operating System :: OS Independent
Classifier: Programming Language :: Python :: 3 :: Only
Classifier: Programming Language :: Python :: 3.6
Classifier: Programming Language :: Python :: 3.7
Classifier: Programming Language :: Python :: 3.8
Classifier: Topic :: Utilities
Provides-Extra: test
Provides-Extra: doc
